ChangeLog
MANIFEST
Makefile
README
TODO
ez_setup.py
install.sh
setup.cfg
setup.py
doc/devel/pres-general/Makefile
doc/devel/pres-general/src/ClassDiagGeneralArchi.jpg
doc/devel/pres-general/src/arch2.png
doc/devel/pres-general/src/collecter.jpg
doc/devel/pres-general/src/diag1.png
doc/devel/pres-general/src/diag2.png
doc/devel/pres-general/src/diag5.png
doc/devel/pres-general/src/diag6.png
doc/devel/pres-general/src/diag7.png
doc/devel/pres-general/src/exploiter.jpg
doc/devel/pres-general/src/general.jpg
doc/devel/pres-general/src/general.png
doc/devel/pres-general/src/parametrer.jpg
doc/devel/pres-general/src/presentation-generale.xml
doc/devel/pres-general/src/scruter.jpg
doc/devel/pres-general/src/stocker.jpg
doc/devel/pres-general/src/xmlrpc.jpg
doc/manual/Makefile
doc/manual/src/INDEX
doc/manual/src/admin.xml
doc/manual/src/dev.xml
doc/manual/src/manual.xml
doc/manual/src/style.css
doc/manual/src/tool.xml
doc/manual/src/user.xml
doc/rapport/Makefile
doc/rapport/src/INDEX
doc/rapport/src/abrev.xml
doc/rapport/src/acro.xml
doc/rapport/src/admin.xml
doc/rapport/src/anx.xml
doc/rapport/src/bib.xml
doc/rapport/src/cdc.xml
doc/rapport/src/conc.xml
doc/rapport/src/devplan.xml
doc/rapport/src/etudtechno.xml
doc/rapport/src/exist.xml
doc/rapport/src/glos.xml
doc/rapport/src/intro.xml
doc/rapport/src/logarchi.xml
doc/rapport/src/qualite.xml
doc/rapport/src/rapport.xml
doc/rapport/src/style.css
doc/rapport/src/techspec.xml
doc/rapport/src/user.xml
doc/rapport/src/images/ClassDiagGeneralArchi.jpg
doc/rapport/src/images/agent-devplan.dia
doc/rapport/src/images/agent-devplan.png
doc/rapport/src/images/agent_plugin-devplan.dia
doc/rapport/src/images/agent_plugin-devplan.png
doc/rapport/src/images/charte01.png
doc/rapport/src/images/charte02.png
doc/rapport/src/images/charte03.png
doc/rapport/src/images/charte04.png
doc/rapport/src/images/charte05.png
doc/rapport/src/images/charte06.png
doc/rapport/src/images/charte07.png
doc/rapport/src/images/charte08.png
src/core/net6mon.egg-info/PKG-INFO
src/core/net6mon.egg-info/SOURCES.txt
src/core/net6mon.egg-info/requires.txt
src/core/net6mon.egg-info/top_level.txt
