Metadata-Version: 1.0
Name: net6mon
Version: 0.0.1.dev-r737
Summary: Net6mon network monitoring project
Home-page: http://almach.cuefa.inpg.fr
Author: Francois Visconte, Maxime Ducros, Pierre-Loic Boyer, Yoann Periola, Romain Faccio
Author-email: net6mon@kh3.org
License: UNKNOWN
Download-URL: http://almach.cuefa.inpg.fr/
Platform: any
Classifier: Development Status :: 1 - Planning
Classifier: Intended Audience :: Developers
Classifier: License :: OSI Approved :: GNU General Public License (GPL)
Classifier: Topic :: System :: Networking :: Monitoring
Classifier: Programming Language :: Python
Classifier: Operating System :: Microsoft :: Windows
Classifier: Operating System :: Unix
